{
	"name": "exists_dataflow",
	"properties": {
		"type": "MappingDataFlow",
		"typeProperties": {
			"sources": [
				{
					"dataset": {
						"referenceName": "ds_common",
						"type": "DatasetReference"
					},
					"name": "source1"
				},
				{
					"dataset": {
						"referenceName": "ds_common",
						"type": "DatasetReference"
					},
					"name": "source2"
				}
			],
			"sinks": [
				{
					"dataset": {
						"referenceName": "ds_sql_common",
						"type": "DatasetReference"
					},
					"name": "sink1"
				}
			],
			"transformations": [
				{
					"name": "Exists1"
				}
			],
			"script": "parameters{\n\tdepartment as integer (1),\n\tdept_id as integer (1)\n}\nsource(output(\n\t\temp_id as short,\n\t\tName as string,\n\t\tdepartment as short,\n\t\tcountry as string\n\t),\n\tallowSchemaDrift: true,\n\tvalidateSchema: false,\n\tignoreNoFilesFound: false) ~> source1\nsource(output(\n\t\tdeptid as short,\n\t\tdeptname as string\n\t),\n\tallowSchemaDrift: true,\n\tvalidateSchema: false,\n\tignoreNoFilesFound: false) ~> source2\nsource1, source2 exists(department == deptid,\n\tnegate:false,\n\tbroadcast: 'auto')~> Exists1\nExists1 sink(allowSchemaDrift: true,\n\tvalidateSchema: false,\n\tdeletable:false,\n\tinsertable:true,\n\tupdateable:false,\n\tupsertable:false,\n\tformat: 'table',\n\tskipDuplicateMapInputs: true,\n\tskipDuplicateMapOutputs: true,\n\terrorHandlingOption: 'stopOnFirstError',\n\tpartitionBy('hash', 1)) ~> sink1"
		}
	}
}